kktool/__init__.py
kktool/common_tool.py
kktool/sqlite/__init__.py
kktool/sqlite/liteTool.py
kktool-0.0.1.dist-info/LICENSE
kktool-0.0.1.dist-info/METADATA
kktool-0.0.1.dist-info/WHEEL
kktool-0.0.1.dist-info/top_level.txt
kktool-0.0.1.dist-info/RECORD
