Metadata-Version: 2.1
Name: kktool
Version: 0.0.1
Summary: korp's tool for many things
Home-page: https://cn.bing.com/
Author: korp
Author-email: akai_sola@qq.com
License: UNKNOWN
Platform: UNKNOWN
Classifier: Programming Language :: Python :: 3
Classifier: License :: OSI Approved :: MIT License
Classifier: Operating System :: OS Independent
License-File: LICENSE
